nonebot_plugin_wantwords/__init__.py
nonebot_plugin_wantwords/config.py
nonebot_plugin_wantwords/getWords.py
nonebot_plugin_wantwords-0.1.0.dist-info/LICENSE
nonebot_plugin_wantwords-0.1.0.dist-info/METADATA
nonebot_plugin_wantwords-0.1.0.dist-info/WHEEL
nonebot_plugin_wantwords-0.1.0.dist-info/top_level.txt
nonebot_plugin_wantwords-0.1.0.dist-info/RECORD
