Metadata-Version: 2.1
Name: nonebot-plugin-wantwords
Version: 0.1.0
Summary: use wantwords as a plugin of nonebot
Home-page: https://github.com/limnium/nonebot_plugin_wantwords
Author: limnium
Author-email: limnium@yeah.com
Keywords: nonebot2,nonebot,nonebot_plugin
Platform: any
Classifier: Programming Language :: Python :: 3
Classifier: License :: OSI Approved :: MIT License
Classifier: Operating System :: OS Independent
License-File: LICENSE
Requires-Dist: nonebot-adapter-onebot (<3.0.0,>=2.0.0-beta.1)
Requires-Dist: nonebot2 (<3.0.0,>=2.0.0-beta.1)
Requires-Dist: httpx (>=0.19.0)
